MANIFEST.in
README.md
setup.cfg
setup.py
django_sms_toolkit/__init__.py
django_sms_toolkit/admin.py
django_sms_toolkit/apps.py
django_sms_toolkit/models.py
django_sms_toolkit/settings.py
django_sms_toolkit/tasks.py
django_sms_toolkit/urls.py
django_sms_toolkit/views.py
django_sms_toolkit.egg-info/PKG-INFO
django_sms_toolkit.egg-info/SOURCES.txt
django_sms_toolkit.egg-info/dependency_links.txt
django_sms_toolkit.egg-info/requires.txt
django_sms_toolkit.egg-info/top_level.txt
django_sms_toolkit/migrations/0001_initial.py
django_sms_toolkit/migrations/0002_alter_model_options.py
django_sms_toolkit/migrations/0003_alter_recipient_field.py
django_sms_toolkit/migrations/0004_alter_exception_message_field.py
django_sms_toolkit/migrations/__init__.py